LICENSE.txt
README.md
setup.cfg
setup.py
psapy/BHPExample.py
psapy/BeggsandBrill.py
psapy/DB_Example.py
psapy/FluidProps.py
psapy/GasProp.py
psapy/Hagendornandbrown.py
psapy/OilProps.py
psapy/Solving_Intersections.py
psapy/Vogel.py
psapy/WaterProps.py
psapy/__init__.py
psapy/test.py
psapy.egg-info/PKG-INFO
psapy.egg-info/SOURCES.txt
psapy.egg-info/dependency_links.txt
psapy.egg-info/requires.txt
psapy.egg-info/top_level.txt