Metadata-Version: 2.1
Name: psapy
Version: 0.5
Summary: Production System Analysis
Home-page: https://github.com/orkahub/production_systems_analysis
Author: Orkahub Energy
Author-email: orkahub@gmail.com
License: MIT
Download-URL: https://github.com/orkahub/production_systems_analysis/archive/v_03.tar.gz
Keywords: RESERVOIR,ENERGY,OIL,GAS,PRODUCTION,VLP,IPR
Platform: UNKNOWN
Classifier: Development Status :: 3 - Alpha
Classifier: Intended Audience :: Developers
Classifier: Topic :: Software Development :: Build Tools
Classifier: License :: OSI Approved :: MIT License
Classifier: Programming Language :: Python :: 3
Classifier: Programming Language :: Python :: 3.4
Classifier: Programming Language :: Python :: 3.5
Classifier: Programming Language :: Python :: 3.6
Classifier: Programming Language :: Python :: 3.7
Classifier: Programming Language :: Python :: 3.8
License-File: LICENSE.txt
